[
  {
    "name": "hover:/",
    "selector": "/",
    "delta": "domLen 46578->46578",
    "screenshot": "hover-0.png"
  },
  {
    "name": "hover:/product",
    "selector": "/product",
    "delta": "domLen 46578->46578",
    "screenshot": "hover-1.png"
  },
  {
    "name": "hover:/specifications",
    "selector": "/specifications",
    "delta": "domLen 46578->46578",
    "screenshot": "hover-2.png"
  },
  {
    "name": "hover:/about",
    "selector": "/about",
    "delta": "domLen 46578->46578",
    "screenshot": "hover-3.png"
  },
  {
    "name": "hover:/pricing",
    "selector": "/pricing",
    "delta": "domLen 46578->46578",
    "screenshot": "hover-4.png"
  },
  {
    "name": "hover:/contact",
    "selector": "/contact",
    "delta": "domLen 46578->46578",
    "screenshot": "hover-5.png"
  },
  {
    "name": "scroll-bottom",
    "delta": "footer revealed",
    "screenshot": "scrolled-bottom.png"
  },
  {
    "name": "mobile-hamburger",
    "selector": "header button",
    "delta": "domLen 46578->46758, mobile nav panel opens",
    "screenshot": "mobile-menu-open.png"
  }
]