{
	"fonts": [
		"ui-sans-serif, system-ui, sans-serif, \"Apple Color Emoji\", \"Segoe UI Emoji\", \"Segoe UI Symbol\", \"Noto Color Emoji\"",
		"Manrope, system-ui, sans-serif"
	],
	"imgs": [],
	"links": [
		{
			"t": "Agenforce",
			"h": "http://localhost:8845/index.html"
		},
		{
			"t": "Forgot password?",
			"h": "http://localhost:8845/login.html#"
		},
		{
			"t": "Sign up",
			"h": "http://localhost:8845/signup.html"
		}
	],
	"nodes": [
		{
			"tag": "BODY",
			"cls": "",
			"text": "Agenforce\n\t\t\t\t\n\t\t\t\n\n\t\t\t\n\t\t\t\t\n\t\t\t\t\tWelcome back\n\t\t\t\t\tSign in ",
			"color": "rgb(10, 10, 10)",
			"bg": "rgb(255, 255, 255)",
			"font": "ui-sans-serif",
			"fs": "16px",
			"fw": "400",
			"ls": "normal",
			"lh": "24px",
			"border": "0px solid rgb(10, 10, 10)",
			"radius": "0px",
			"pad": "0px",
			"w": 1440,
			"h": 900
		},
		{
			"tag": "DIV",
			"cls": "auth-page",
			"text": "Agenforce\n\t\t\t\t\n\t\t\t\n\n\t\t\t\n\t\t\t\t\n\t\t\t\t\tWelcome back\n\t\t\t\t\tSign in ",
			"color": "rgb(10, 10, 10)",
			"bg": "rgba(0, 0, 0, 0)",
			"font": "ui-sans-serif",
			"fs": "16px",
			"fw": "400",
			"ls": "normal",
			"lh": "24px",
			"border": "0px solid rgb(10, 10, 10)",
			"radius": "0px",
			"pad": "0px",
			"w": 1440,
			"h": 900
		},
		{
			"tag": "DIV",
			"cls": "auth-navbar",
			"text": "Agenforce",
			"color": "rgb(10, 10, 10)",
			"bg": "rgba(0, 0, 0, 0)",
			"font": "ui-sans-serif",
			"fs": "16px",
			"fw": "400",
			"ls": "normal",
			"lh": "24px",
			"border": "0px solid rgb(10, 10, 10)",
			"radius": "0px",
			"pad": "24px",
			"w": 1440,
			"h": 69
		},
		{
			"tag": "A",
			"cls": "navbar-logo",
			"text": "Agenforce",
			"color": "rgb(10, 10, 10)",
			"bg": "rgba(0, 0, 0, 0)",
			"font": "ui-sans-serif",
			"fs": "16px",
			"fw": "400",
			"ls": "normal",
			"lh": "24px",
			"border": "0px solid rgb(10, 10, 10)",
			"radius": "0px",
			"pad": "0px",
			"w": 1392,
			"h": 21
		},
		{
			"tag": "svg",
			"cls": "[object SVGAnimatedString]",
			"text": "",
			"color": "rgb(10, 10, 10)",
			"bg": "rgba(0, 0, 0, 0)",
			"font": "ui-sans-serif",
			"fs": "16px",
			"fw": "400",
			"ls": "normal",
			"lh": "24px",
			"border": "0px solid rgb(10, 10, 10)",
			"radius": "0px",
			"pad": "0px",
			"w": 20,
			"h": 15
		},
		{
			"tag": "SPAN",
			"cls": "navbar-logo-text",
			"text": "Agenforce",
			"color": "rgb(82, 82, 82)",
			"bg": "rgba(0, 0, 0, 0)",
			"font": "ui-sans-serif",
			"fs": "14px",
			"fw": "400",
			"ls": "normal",
			"lh": "21px",
			"border": "0px solid rgb(82, 82, 82)",
			"radius": "0px",
			"pad": "0px",
			"w": 66,
			"h": 21
		},
		{
			"tag": "MAIN",
			"cls": "auth-main",
			"text": "Welcome back\n\t\t\t\t\tSign in to your account to continue\n\n\t\t\t\t\t",
			"color": "rgb(10, 10, 10)",
			"bg": "rgba(0, 0, 0, 0)",
			"font": "ui-sans-serif",
			"fs": "16px",
			"fw": "400",
			"ls": "normal",
			"lh": "24px",
			"border": "0px solid rgb(10, 10, 10)",
			"radius": "0px",
			"pad": "48px 16px",
			"w": 1440,
			"h": 831
		},
		{
			"tag": "DIV",
			"cls": "auth-card",
			"text": "Welcome back\n\t\t\t\t\tSign in to your account to continue\n\n\t\t\t\t\t",
			"color": "rgb(10, 10, 10)",
			"bg": "rgba(0, 0, 0, 0)",
			"font": "ui-sans-serif",
			"fs": "16px",
			"fw": "400",
			"ls": "normal",
			"lh": "24px",
			"border": "0px solid rgb(10, 10, 10)",
			"radius": "0px",
			"pad": "0px",
			"w": 448,
			"h": 610
		},
		{
			"tag": "H1",
			"cls": "auth-heading font-display font-bold",
			"text": "Welcome back",
			"color": "rgb(10, 10, 10)",
			"bg": "rgba(0, 0, 0, 0)",
			"font": "Manrope",
			"fs": "36px",
			"fw": "700",
			"ls": "-0.9px",
			"lh": "54px",
			"border": "0px solid rgb(10, 10, 10)",
			"radius": "0px",
			"pad": "0px",
			"w": 448,
			"h": 54
		},
		{
			"tag": "P",
			"cls": "auth-subheading",
			"text": "Sign in to your account to continue",
			"color": "rgb(115, 115, 115)",
			"bg": "rgba(0, 0, 0, 0)",
			"font": "ui-sans-serif",
			"fs": "18px",
			"fw": "400",
			"ls": "normal",
			"lh": "27px",
			"border": "0px solid rgb(115, 115, 115)",
			"radius": "0px",
			"pad": "0px",
			"w": 448,
			"h": 27
		},
		{
			"tag": "BUTTON",
			"cls": "auth-social-btn",
			"text": "Continue with Google",
			"color": "rgb(10, 10, 10)",
			"bg": "rgb(255, 255, 255)",
			"font": "ui-sans-serif",
			"fs": "14px",
			"fw": "400",
			"ls": "normal",
			"lh": "21px",
			"border": "1px solid rgb(229, 229, 229)",
			"radius": "10px",
			"pad": "12px 16px",
			"w": 448,
			"h": 47
		},
		{
			"tag": "BUTTON",
			"cls": "auth-social-btn",
			"text": "Continue with GitHub",
			"color": "rgb(10, 10, 10)",
			"bg": "rgb(255, 255, 255)",
			"font": "ui-sans-serif",
			"fs": "14px",
			"fw": "400",
			"ls": "normal",
			"lh": "21px",
			"border": "1px solid rgb(229, 229, 229)",
			"radius": "10px",
			"pad": "12px 16px",
			"w": 448,
			"h": 47
		},
		{
			"tag": "DIV",
			"cls": "auth-divider",
			"text": "Or continue with email",
			"color": "rgb(10, 10, 10)",
			"bg": "rgba(0, 0, 0, 0)",
			"font": "ui-sans-serif",
			"fs": "16px",
			"fw": "400",
			"ls": "normal",
			"lh": "24px",
			"border": "0px solid rgb(10, 10, 10)",
			"radius": "0px",
			"pad": "0px",
			"w": 448,
			"h": 21
		},
		{
			"tag": "FORM",
			"cls": "auth-form",
			"text": "Email address\n\t\t\t\t\t\t\t\n\t\t\t\t\t\t\n\n\t\t\t\t\t\t\n\t\t\t\t\t\t\t\n\t\t\t\t\t\t\t\tPasswor",
			"color": "rgb(10, 10, 10)",
			"bg": "rgba(0, 0, 0, 0)",
			"font": "ui-sans-serif",
			"fs": "16px",
			"fw": "400",
			"ls": "normal",
			"lh": "24px",
			"border": "0px solid rgb(10, 10, 10)",
			"radius": "0px",
			"pad": "0px",
			"w": 448,
			"h": 249
		},
		{
			"tag": "P",
			"cls": "auth-footer",
			"text": "Don't have an account? Sign up",
			"color": "rgb(115, 115, 115)",
			"bg": "rgba(0, 0, 0, 0)",
			"font": "ui-sans-serif",
			"fs": "14px",
			"fw": "400",
			"ls": "normal",
			"lh": "21px",
			"border": "0px solid rgb(115, 115, 115)",
			"radius": "0px",
			"pad": "0px",
			"w": 448,
			"h": 21
		}
	]
}
