{
  "fonts": [
    "Geist, sans-serif",
    "Arial"
  ],
  "imgs": [],
  "links": [
    {
      "t": "",
      "h": "http://localhost:8731/index.html"
    },
    {
      "t": "Overview",
      "h": "http://localhost:8731/system-overview.html"
    },
    {
      "t": "About",
      "h": "http://localhost:8731/about.html"
    },
    {
      "t": "Contact",
      "h": "http://localhost:8731/contact.html"
    },
    {
      "t": "Integrations",
      "h": "http://localhost:8731/integrations.html"
    },
    {
      "t": "",
      "h": "http://localhost:8731/index.html"
    },
    {
      "t": "Overview",
      "h": "http://localhost:8731/system-overview.html"
    },
    {
      "t": "Sign up",
      "h": "http://localhost:8731/about.html#"
    },
    {
      "t": "",
      "h": "http://localhost:8731/about.html#"
    },
    {
      "t": "",
      "h": "http://localhost:8731/about.html#"
    },
    {
      "t": "",
      "h": "http://localhost:8731/about.html#"
    },
    {
      "t": "",
      "h": "http://localhost:8731/about.html#"
    },
    {
      "t": "Overview",
      "h": "http://localhost:8731/system-overview.html"
    },
    {
      "t": "About",
      "h": "http://localhost:8731/about.html"
    },
    {
      "t": "Careers",
      "h": "http://localhost:8731/about.html#"
    },
    {
      "t": "Contact",
      "h": "http://localhost:8731/contact.html"
    },
    {
      "t": "Blog",
      "h": "http://localhost:8731/about.html#"
    },
    {
      "t": "Changelog",
      "h": "http://localhost:8731/about.html#"
    },
    {
      "t": "Pricing",
      "h": "http://localhost:8731/about.html#"
    }
  ],
  "nodes": [
    {
      "tag": "BODY",
      "cls": "",
      "text": "✕\n\t\t\t\t\n\t\t\t\n\t\t\t\n\t\t\t\tOverview\n\t\t\t\tAbout\n\t\t\t\tContact\n\t\t\t\tIntegr",
      "color": "oklch(0.29 0 0)",
      "bg": "rgb(255, 255, 255)",
      "font": "Geist",
      "fs": "16px",
      "fw": "400",
      "ls": "normal",
      "lh": "normal",
      "border": "0px none oklch(0.29 0 0)",
      "radius": "0px",
      "pad": "0px",
      "w": 1440,
      "h": 3418
    },
    {
      "tag": "HEADER",
      "cls": "",
      "text": "Overview\n\t\t\t\t\tSign up",
      "color": "oklch(0.29 0 0)",
      "bg": "rgb(255, 255, 255)",
      "font": "Geist",
      "fs": "16px",
      "fw": "400",
      "ls": "normal",
      "lh": "normal",
      "border": "",
      "radius": "0px",
      "pad": "0px",
      "w": 1440,
      "h": 49
    },
    {
      "tag": "DIV",
      "cls": "header-inner",
      "text": "Overview\n\t\t\t\t\tSign up",
      "color": "oklch(0.29 0 0)",
      "bg": "rgba(0, 0, 0, 0)",
      "font": "Geist",
      "fs": "16px",
      "fw": "400",
      "ls": "normal",
      "lh": "normal",
      "border": "0px none oklch(0.29 0 0)",
      "radius": "0px",
      "pad": "0px 16px",
      "w": 1440,
      "h": 37
    },
    {
      "tag": "A",
      "cls": "header-logo",
      "text": "",
      "color": "oklch(0.29 0 0)",
      "bg": "rgba(0, 0, 0, 0)",
      "font": "Geist",
      "fs": "16px",
      "fw": "400",
      "ls": "normal",
      "lh": "normal",
      "border": "0px none oklch(0.29 0 0)",
      "radius": "0px",
      "pad": "0px",
      "w": 116,
      "h": 37
    },
    {
      "tag": "svg",
      "cls": "[object SVGAnimatedString]",
      "text": "",
      "color": "oklch(0.29 0 0)",
      "bg": "rgba(0, 0, 0, 0)",
      "font": "Geist",
      "fs": "16px",
      "fw": "400",
      "ls": "normal",
      "lh": "normal",
      "border": "0px none oklch(0.29 0 0)",
      "radius": "0px",
      "pad": "0px",
      "w": 116,
      "h": 32
    },
    {
      "tag": "DIV",
      "cls": "header-right",
      "text": "Overview\n\t\t\t\t\tSign up",
      "color": "oklch(0.29 0 0)",
      "bg": "rgba(0, 0, 0, 0)",
      "font": "Geist",
      "fs": "16px",
      "fw": "400",
      "ls": "normal",
      "lh": "normal",
      "border": "0px none oklch(0.29 0 0)",
      "radius": "0px",
      "pad": "0px",
      "w": 203,
      "h": 34
    },
    {
      "tag": "A",
      "cls": "nav-link",
      "text": "Overview",
      "color": "oklch(0.29 0 0)",
      "bg": "rgba(0, 0, 0, 0)",
      "font": "Geist",
      "fs": "16px",
      "fw": "600",
      "ls": "normal",
      "lh": "normal",
      "border": "0px none oklch(0.29 0 0)",
      "radius": "0px",
      "pad": "0px",
      "w": 72,
      "h": 21
    },
    {
      "tag": "A",
      "cls": "btn-signup",
      "text": "Sign up",
      "color": "rgb(255, 255, 255)",
      "bg": "oklch(0.29 0 0)",
      "font": "Geist",
      "fs": "14px",
      "fw": "600",
      "ls": "normal",
      "lh": "normal",
      "border": "0px none rgb(255, 255, 255)",
      "radius": "0px",
      "pad": "8px 16px",
      "w": 83,
      "h": 34
    },
    {
      "tag": "BUTTON",
      "cls": "btn-search",
      "text": "",
      "color": "rgb(255, 255, 255)",
      "bg": "oklch(0.29 0 0)",
      "font": "Arial",
      "fs": "13.3333px",
      "fw": "400",
      "ls": "normal",
      "lh": "normal",
      "border": "0px none rgb(255, 255, 255)",
      "radius": "0px",
      "pad": "0px",
      "w": 32,
      "h": 32
    },
    {
      "tag": "SECTION",
      "cls": "hero",
      "text": "About us",
      "color": "oklch(0.29 0 0)",
      "bg": "rgba(0, 0, 0, 0)",
      "font": "Geist",
      "fs": "16px",
      "fw": "400",
      "ls": "normal",
      "lh": "normal",
      "border": "0px none oklch(0.29 0 0)",
      "radius": "0px",
      "pad": "200px 16px 64px",
      "w": 1440,
      "h": 408
    },
    {
      "tag": "H1",
      "cls": "",
      "text": "About us",
      "color": "oklch(0.29 0 0)",
      "bg": "rgba(0, 0, 0, 0)",
      "font": "Geist",
      "fs": "144px",
      "fw": "700",
      "ls": "-5.76px",
      "lh": "144px",
      "border": "0px none oklch(0.29 0 0)",
      "radius": "0px",
      "pad": "0px",
      "w": 1408,
      "h": 144
    },
    {
      "tag": "SECTION",
      "cls": "mission",
      "text": "A team of former sales leads, ops pros, and product builders",
      "color": "oklch(0.29 0 0)",
      "bg": "oklch(0.8 0.0456 250.63)",
      "font": "Geist",
      "fs": "16px",
      "fw": "400",
      "ls": "normal",
      "lh": "normal",
      "border": "0px none oklch(0.29 0 0)",
      "radius": "0px",
      "pad": "192px 16px",
      "w": 1440,
      "h": 468
    },
    {
      "tag": "P",
      "cls": "",
      "text": "A team of former sales leads, ops pros, and product builders",
      "color": "oklch(0.29 0 0)",
      "bg": "rgba(0, 0, 0, 0)",
      "font": "Geist",
      "fs": "30px",
      "fw": "400",
      "ls": "normal",
      "lh": "42px",
      "border": "0px none oklch(0.29 0 0)",
      "radius": "0px",
      "pad": "0px",
      "w": 768,
      "h": 84
    },
    {
      "tag": "SECTION",
      "cls": "experience",
      "text": "We got experience\n\t\t\t\t\n\t\t\t\t\tWe're a team of former sales pro",
      "color": "oklch(0.29 0 0)",
      "bg": "oklch(0.6 0.1499 37.55)",
      "font": "Geist",
      "fs": "16px",
      "fw": "400",
      "ls": "normal",
      "lh": "normal",
      "border": "0px none oklch(0.29 0 0)",
      "radius": "0px",
      "pad": "96px 32px",
      "w": 1440,
      "h": 451
    },
    {
      "tag": "DIV",
      "cls": "experience-inner",
      "text": "We got experience\n\t\t\t\t\n\t\t\t\t\tWe're a team of former sales pro",
      "color": "oklch(0.29 0 0)",
      "bg": "rgba(0, 0, 0, 0)",
      "font": "Geist",
      "fs": "16px",
      "fw": "400",
      "ls": "normal",
      "lh": "normal",
      "border": "0px none oklch(0.29 0 0)",
      "radius": "0px",
      "pad": "0px",
      "w": 1024,
      "h": 259
    },
    {
      "tag": "H2",
      "cls": "",
      "text": "We got experience",
      "color": "oklch(0.29 0 0)",
      "bg": "rgba(0, 0, 0, 0)",
      "font": "Geist",
      "fs": "100.8px",
      "fw": "700",
      "ls": "-4.032px",
      "lh": "100.8px",
      "border": "0px none oklch(0.29 0 0)",
      "radius": "0px",
      "pad": "0px",
      "w": 1024,
      "h": 101
    },
    {
      "tag": "P",
      "cls": "",
      "text": "We're a team of former sales professionals, operations leads",
      "color": "oklch(0.29 0 0)",
      "bg": "rgba(0, 0, 0, 0)",
      "font": "Geist",
      "fs": "18px",
      "fw": "400",
      "ls": "normal",
      "lh": "31.5px",
      "border": "0px none oklch(0.29 0 0)",
      "radius": "0px",
      "pad": "0px",
      "w": 576,
      "h": 126
    },
    {
      "tag": "SECTION",
      "cls": "team",
      "text": "Our team\n\t\t\t\n\t\t\t\n\t\t\t\n\t\t\t\t\n\t\t\t\t\t\n\t\t\t\t\tCory Swanson\n\t\t\t\t\tCo-fo",
      "color": "oklch(0.29 0 0)",
      "bg": "rgba(0, 0, 0, 0)",
      "font": "Geist",
      "fs": "16px",
      "fw": "400",
      "ls": "normal",
      "lh": "normal",
      "border": "0px none oklch(0.29 0 0)",
      "radius": "0px",
      "pad": "64px 16px",
      "w": 1440,
      "h": 1385
    },
    {
      "tag": "DIV",
      "cls": "team-header",
      "text": "Our team",
      "color": "oklch(0.29 0 0)",
      "bg": "rgba(0, 0, 0, 0)",
      "font": "Geist",
      "fs": "16px",
      "fw": "400",
      "ls": "normal",
      "lh": "normal",
      "border": "0px none oklch(0.29 0 0)",
      "radius": "0px",
      "pad": "0px",
      "w": 1408,
      "h": 147
    },
    {
      "tag": "H2",
      "cls": "",
      "text": "Our team",
      "color": "oklch(0.29 0 0)",
      "bg": "rgba(0, 0, 0, 0)",
      "font": "Geist",
      "fs": "115.2px",
      "fw": "700",
      "ls": "-4.608px",
      "lh": "115.2px",
      "border": "0px none oklch(0.29 0 0)",
      "radius": "0px",
      "pad": "0px 0px 32px",
      "w": 1408,
      "h": 147
    },
    {
      "tag": "DIV",
      "cls": "team-separator",
      "text": "",
      "color": "oklch(0.29 0 0)",
      "bg": "rgba(0, 0, 0, 0)",
      "font": "Geist",
      "fs": "16px",
      "fw": "400",
      "ls": "normal",
      "lh": "normal",
      "border": "",
      "radius": "0px",
      "pad": "0px",
      "w": 1408,
      "h": 1
    },
    {
      "tag": "DIV",
      "cls": "team-grid",
      "text": "Cory Swanson\n\t\t\t\t\tCo-founder & CEO\n\t\t\t\t\n\t\t\t\t\n\t\t\t\t\t\n\t\t\t\t\tMaya",
      "color": "oklch(0.29 0 0)",
      "bg": "rgba(0, 0, 0, 0)",
      "font": "Geist",
      "fs": "16px",
      "fw": "400",
      "ls": "normal",
      "lh": "normal",
      "border": "0px none oklch(0.29 0 0)",
      "radius": "0px",
      "pad": "0px",
      "w": 1408,
      "h": 1060
    },
    {
      "tag": "DIV",
      "cls": "team-card",
      "text": "Cory Swanson\n\t\t\t\t\tCo-founder & CEO",
      "color": "oklch(0.29 0 0)",
      "bg": "rgba(0, 0, 0, 0)",
      "font": "Geist",
      "fs": "16px",
      "fw": "400",
      "ls": "normal",
      "lh": "normal",
      "border": "1px dashed oklab(0.29 0 0 / 0.2)",
      "radius": "0px",
      "pad": "24px",
      "w": 469,
      "h": 530
    },
    {
      "tag": "DIV",
      "cls": "team-photo",
      "text": "",
      "color": "oklch(0.29 0 0)",
      "bg": "oklch(0.83 0.0018 325.59)",
      "font": "Geist",
      "fs": "16px",
      "fw": "400",
      "ls": "normal",
      "lh": "normal",
      "border": "0px none oklch(0.29 0 0)",
      "radius": "0px",
      "pad": "0px",
      "w": 419,
      "h": 419
    },
    {
      "tag": "DIV",
      "cls": "team-name",
      "text": "Cory Swanson",
      "color": "oklch(0.29 0 0)",
      "bg": "rgba(0, 0, 0, 0)",
      "font": "Geist",
      "fs": "18px",
      "fw": "700",
      "ls": "normal",
      "lh": "normal",
      "border": "0px none oklch(0.29 0 0)",
      "radius": "0px",
      "pad": "0px",
      "w": 419,
      "h": 23
    },
    {
      "tag": "DIV",
      "cls": "team-role",
      "text": "Co-founder & CEO",
      "color": "oklab(0.29 0 0 / 0.6)",
      "bg": "rgba(0, 0, 0, 0)",
      "font": "Geist",
      "fs": "14px",
      "fw": "400",
      "ls": "normal",
      "lh": "normal",
      "border": "0px none oklab(0.29 0 0 / 0.6)",
      "radius": "0px",
      "pad": "0px",
      "w": 419,
      "h": 18
    },
    {
      "tag": "DIV",
      "cls": "team-card",
      "text": "Maya Chen\n\t\t\t\t\tCo-founder & CTO",
      "color": "oklch(0.29 0 0)",
      "bg": "rgba(0, 0, 0, 0)",
      "font": "Geist",
      "fs": "16px",
      "fw": "400",
      "ls": "normal",
      "lh": "normal",
      "border": "1px dashed oklab(0.29 0 0 / 0.2)",
      "radius": "0px",
      "pad": "24px",
      "w": 469,
      "h": 530
    },
    {
      "tag": "DIV",
      "cls": "team-photo",
      "text": "",
      "color": "oklch(0.29 0 0)",
      "bg": "oklch(0.83 0.0018 325.59)",
      "font": "Geist",
      "fs": "16px",
      "fw": "400",
      "ls": "normal",
      "lh": "normal",
      "border": "0px none oklch(0.29 0 0)",
      "radius": "0px",
      "pad": "0px",
      "w": 419,
      "h": 419
    },
    {
      "tag": "DIV",
      "cls": "team-name",
      "text": "Maya Chen",
      "color": "oklch(0.29 0 0)",
      "bg": "rgba(0, 0, 0, 0)",
      "font": "Geist",
      "fs": "18px",
      "fw": "700",
      "ls": "normal",
      "lh": "normal",
      "border": "0px none oklch(0.29 0 0)",
      "radius": "0px",
      "pad": "0px",
      "w": 419,
      "h": 23
    },
    {
      "tag": "DIV",
      "cls": "team-role",
      "text": "Co-founder & CTO",
      "color": "oklab(0.29 0 0 / 0.6)",
      "bg": "rgba(0, 0, 0, 0)",
      "font": "Geist",
      "fs": "14px",
      "fw": "400",
      "ls": "normal",
      "lh": "normal",
      "border": "0px none oklab(0.29 0 0 / 0.6)",
      "radius": "0px",
      "pad": "0px",
      "w": 419,
      "h": 18
    },
    {
      "tag": "DIV",
      "cls": "team-card",
      "text": "Jordan Walsh\n\t\t\t\t\tHead of Design",
      "color": "oklch(0.29 0 0)",
      "bg": "rgba(0, 0, 0, 0)",
      "font": "Geist",
      "fs": "16px",
      "fw": "400",
      "ls": "normal",
      "lh": "normal",
      "border": "1px dashed oklab(0.29 0 0 / 0.2)",
      "radius": "0px",
      "pad": "24px",
      "w": 469,
      "h": 530
    },
    {
      "tag": "DIV",
      "cls": "team-photo",
      "text": "",
      "color": "oklch(0.29 0 0)",
      "bg": "oklch(0.83 0.0018 325.59)",
      "font": "Geist",
      "fs": "16px",
      "fw": "400",
      "ls": "normal",
      "lh": "normal",
      "border": "0px none oklch(0.29 0 0)",
      "radius": "0px",
      "pad": "0px",
      "w": 419,
      "h": 419
    },
    {
      "tag": "DIV",
      "cls": "team-name",
      "text": "Jordan Walsh",
      "color": "oklch(0.29 0 0)",
      "bg": "rgba(0, 0, 0, 0)",
      "font": "Geist",
      "fs": "18px",
      "fw": "700",
      "ls": "normal",
      "lh": "normal",
      "border": "0px none oklch(0.29 0 0)",
      "radius": "0px",
      "pad": "0px",
      "w": 419,
      "h": 23
    },
    {
      "tag": "DIV",
      "cls": "team-role",
      "text": "Head of Design",
      "color": "oklab(0.29 0 0 / 0.6)",
      "bg": "rgba(0, 0, 0, 0)",
      "font": "Geist",
      "fs": "14px",
      "fw": "400",
      "ls": "normal",
      "lh": "normal",
      "border": "0px none oklab(0.29 0 0 / 0.6)",
      "radius": "0px",
      "pad": "0px",
      "w": 419,
      "h": 18
    },
    {
      "tag": "DIV",
      "cls": "team-card",
      "text": "Priya Nair\n\t\t\t\t\tHead of Product",
      "color": "oklch(0.29 0 0)",
      "bg": "rgba(0, 0, 0, 0)",
      "font": "Geist",
      "fs": "16px",
      "fw": "400",
      "ls": "normal",
      "lh": "normal",
      "border": "1px dashed oklab(0.29 0 0 / 0.2)",
      "radius": "0px",
      "pad": "24px",
      "w": 469,
      "h": 530
    },
    {
      "tag": "DIV",
      "cls": "team-photo",
      "text": "",
      "color": "oklch(0.29 0 0)",
      "bg": "oklch(0.83 0.0018 325.59)",
      "font": "Geist",
      "fs": "16px",
      "fw": "400",
      "ls": "normal",
      "lh": "normal",
      "border": "0px none oklch(0.29 0 0)",
      "radius": "0px",
      "pad": "0px",
      "w": 419,
      "h": 419
    },
    {
      "tag": "DIV",
      "cls": "team-name",
      "text": "Priya Nair",
      "color": "oklch(0.29 0 0)",
      "bg": "rgba(0, 0, 0, 0)",
      "font": "Geist",
      "fs": "18px",
      "fw": "700",
      "ls": "normal",
      "lh": "normal",
      "border": "0px none oklch(0.29 0 0)",
      "radius": "0px",
      "pad": "0px",
      "w": 419,
      "h": 23
    },
    {
      "tag": "DIV",
      "cls": "team-role",
      "text": "Head of Product",
      "color": "oklab(0.29 0 0 / 0.6)",
      "bg": "rgba(0, 0, 0, 0)",
      "font": "Geist",
      "fs": "14px",
      "fw": "400",
      "ls": "normal",
      "lh": "normal",
      "border": "0px none oklab(0.29 0 0 / 0.6)",
      "radius": "0px",
      "pad": "0px",
      "w": 419,
      "h": 18
    },
    {
      "tag": "DIV",
      "cls": "team-card",
      "text": "Liam Torres\n\t\t\t\t\tLead Engineer",
      "color": "oklch(0.29 0 0)",
      "bg": "rgba(0, 0, 0, 0)",
      "font": "Geist",
      "fs": "16px",
      "fw": "400",
      "ls": "normal",
      "lh": "normal",
      "border": "1px dashed oklab(0.29 0 0 / 0.2)",
      "radius": "0px",
      "pad": "24px",
      "w": 469,
      "h": 530
    },
    {
      "tag": "DIV",
      "cls": "team-photo",
      "text": "",
      "color": "oklch(0.29 0 0)",
      "bg": "oklch(0.83 0.0018 325.59)",
      "font": "Geist",
      "fs": "16px",
      "fw": "400",
      "ls": "normal",
      "lh": "normal",
      "border": "0px none oklch(0.29 0 0)",
      "radius": "0px",
      "pad": "0px",
      "w": 419,
      "h": 419
    },
    {
      "tag": "DIV",
      "cls": "team-name",
      "text": "Liam Torres",
      "color": "oklch(0.29 0 0)",
      "bg": "rgba(0, 0, 0, 0)",
      "font": "Geist",
      "fs": "18px",
      "fw": "700",
      "ls": "normal",
      "lh": "normal",
      "border": "0px none oklch(0.29 0 0)",
      "radius": "0px",
      "pad": "0px",
      "w": 419,
      "h": 23
    },
    {
      "tag": "DIV",
      "cls": "team-role",
      "text": "Lead Engineer",
      "color": "oklab(0.29 0 0 / 0.6)",
      "bg": "rgba(0, 0, 0, 0)",
      "font": "Geist",
      "fs": "14px",
      "fw": "400",
      "ls": "normal",
      "lh": "normal",
      "border": "0px none oklab(0.29 0 0 / 0.6)",
      "radius": "0px",
      "pad": "0px",
      "w": 419,
      "h": 18
    },
    {
      "tag": "DIV",
      "cls": "team-card",
      "text": "Aria Hoffman\n\t\t\t\t\tHead of Sales",
      "color": "oklch(0.29 0 0)",
      "bg": "rgba(0, 0, 0, 0)",
      "font": "Geist",
      "fs": "16px",
      "fw": "400",
      "ls": "normal",
      "lh": "normal",
      "border": "1px dashed oklab(0.29 0 0 / 0.2)",
      "radius": "0px",
      "pad": "24px",
      "w": 469,
      "h": 530
    },
    {
      "tag": "DIV",
      "cls": "team-photo",
      "text": "",
      "color": "oklch(0.29 0 0)",
      "bg": "oklch(0.83 0.0018 325.59)",
      "font": "Geist",
      "fs": "16px",
      "fw": "400",
      "ls": "normal",
      "lh": "normal",
      "border": "0px none oklch(0.29 0 0)",
      "radius": "0px",
      "pad": "0px",
      "w": 419,
      "h": 419
    },
    {
      "tag": "DIV",
      "cls": "team-name",
      "text": "Aria Hoffman",
      "color": "oklch(0.29 0 0)",
      "bg": "rgba(0, 0, 0, 0)",
      "font": "Geist",
      "fs": "18px",
      "fw": "700",
      "ls": "normal",
      "lh": "normal",
      "border": "0px none oklch(0.29 0 0)",
      "radius": "0px",
      "pad": "0px",
      "w": 419,
      "h": 23
    },
    {
      "tag": "DIV",
      "cls": "team-role",
      "text": "Head of Sales",
      "color": "oklab(0.29 0 0 / 0.6)",
      "bg": "rgba(0, 0, 0, 0)",
      "font": "Geist",
      "fs": "14px",
      "fw": "400",
      "ls": "normal",
      "lh": "normal",
      "border": "0px none oklab(0.29 0 0 / 0.6)",
      "radius": "0px",
      "pad": "0px",
      "w": 419,
      "h": 18
    },
    {
      "tag": "FOOTER",
      "cls": "",
      "text": "Overview\n\t\t\t\tAbout\n\t\t\t\tCareers\n\t\t\t\tContact\n\t\t\t\tBlog\n\t\t\t\tChan",
      "color": "oklch(0.29 0 0)",
      "bg": "rgba(0, 0, 0, 0)",
      "font": "Geist",
      "fs": "16px",
      "fw": "400",
      "ls": "normal",
      "lh": "normal",
      "border": "0px none oklch(0.29 0 0)",
      "radius": "0px",
      "pad": "0px",
      "w": 1440,
      "h": 658
    },
    {
      "tag": "DIV",
      "cls": "footer-dividers",
      "text": "",
      "color": "oklch(0.29 0 0)",
      "bg": "rgba(0, 0, 0, 0)",
      "font": "Geist",
      "fs": "16px",
      "fw": "400",
      "ls": "normal",
      "lh": "normal",
      "border": "0px none oklch(0.29 0 0)",
      "radius": "0px",
      "pad": "0px",
      "w": 1440,
      "h": 26
    },
    {
      "tag": "DIV",
      "cls": "",
      "text": "",
      "color": "oklch(0.29 0 0)",
      "bg": "oklch(0.29 0 0)",
      "font": "Geist",
      "fs": "16px",
      "fw": "400",
      "ls": "normal",
      "lh": "normal",
      "border": "0px none oklch(0.29 0 0)",
      "radius": "0px",
      "pad": "0px",
      "w": 1440,
      "h": 2
    },
    {
      "tag": "DIV",
      "cls": "",
      "text": "",
      "color": "oklch(0.29 0 0)",
      "bg": "oklch(0.29 0 0)",
      "font": "Geist",
      "fs": "16px",
      "fw": "400",
      "ls": "normal",
      "lh": "normal",
      "border": "0px none oklch(0.29 0 0)",
      "radius": "0px",
      "pad": "0px",
      "w": 1440,
      "h": 4
    },
    {
      "tag": "DIV",
      "cls": "",
      "text": "",
      "color": "oklch(0.29 0 0)",
      "bg": "oklch(0.29 0 0)",
      "font": "Geist",
      "fs": "16px",
      "fw": "400",
      "ls": "normal",
      "lh": "normal",
      "border": "0px none oklch(0.29 0 0)",
      "radius": "0px",
      "pad": "0px",
      "w": 1440,
      "h": 8
    },
    {
      "tag": "DIV",
      "cls": "",
      "text": "",
      "color": "oklch(0.29 0 0)",
      "bg": "oklch(0.29 0 0)",
      "font": "Geist",
      "fs": "16px",
      "fw": "400",
      "ls": "normal",
      "lh": "normal",
      "border": "0px none oklch(0.29 0 0)",
      "radius": "0px",
      "pad": "0px",
      "w": 1440,
      "h": 12
    },
    {
      "tag": "DIV",
      "cls": "footer-social",
      "text": "",
      "color": "oklch(0.29 0 0)",
      "bg": "oklch(0.29 0 0)",
      "font": "Geist",
      "fs": "16px",
      "fw": "400",
      "ls": "normal",
      "lh": "normal",
      "border": "0px none oklch(0.29 0 0)",
      "radius": "0px",
      "pad": "32px",
      "w": 1440,
      "h": 89
    },
    {
      "tag": "A",
      "cls": "",
      "text": "",
      "color": "rgb(255, 255, 255)",
      "bg": "rgba(0, 0, 0, 0)",
      "font": "Geist",
      "fs": "16px",
      "fw": "400",
      "ls": "normal",
      "lh": "normal",
      "border": "0px none rgb(255, 255, 255)",
      "radius": "0px",
      "pad": "0px",
      "w": 20,
      "h": 25
    },
    {
      "tag": "svg",
      "cls": "[object SVGAnimatedString]",
      "text": "",
      "color": "rgb(255, 255, 255)",
      "bg": "rgba(0, 0, 0, 0)",
      "font": "Geist",
      "fs": "16px",
      "fw": "400",
      "ls": "normal",
      "lh": "normal",
      "border": "0px none rgb(255, 255, 255)",
      "radius": "0px",
      "pad": "0px",
      "w": 20,
      "h": 20
    },
    {
      "tag": "A",
      "cls": "",
      "text": "",
      "color": "rgb(255, 255, 255)",
      "bg": "rgba(0, 0, 0, 0)",
      "font": "Geist",
      "fs": "16px",
      "fw": "400",
      "ls": "normal",
      "lh": "normal",
      "border": "0px none rgb(255, 255, 255)",
      "radius": "0px",
      "pad": "0px",
      "w": 20,
      "h": 25
    },
    {
      "tag": "svg",
      "cls": "[object SVGAnimatedString]",
      "text": "",
      "color": "rgb(255, 255, 255)",
      "bg": "rgba(0, 0, 0, 0)",
      "font": "Geist",
      "fs": "16px",
      "fw": "400",
      "ls": "normal",
      "lh": "normal",
      "border": "0px none rgb(255, 255, 255)",
      "radius": "0px",
      "pad": "0px",
      "w": 20,
      "h": 20
    },
    {
      "tag": "A",
      "cls": "",
      "text": "",
      "color": "rgb(255, 255, 255)",
      "bg": "rgba(0, 0, 0, 0)",
      "font": "Geist",
      "fs": "16px",
      "fw": "400",
      "ls": "normal",
      "lh": "normal",
      "border": "0px none rgb(255, 255, 255)",
      "radius": "0px",
      "pad": "0px",
      "w": 20,
      "h": 25
    },
    {
      "tag": "svg",
      "cls": "[object SVGAnimatedString]",
      "text": "",
      "color": "rgb(255, 255, 255)",
      "bg": "rgba(0, 0, 0, 0)",
      "font": "Geist",
      "fs": "16px",
      "fw": "400",
      "ls": "normal",
      "lh": "normal",
      "border": "0px none rgb(255, 255, 255)",
      "radius": "0px",
      "pad": "0px",
      "w": 20,
      "h": 20
    },
    {
      "tag": "A",
      "cls": "",
      "text": "",
      "color": "rgb(255, 255, 255)",
      "bg": "rgba(0, 0, 0, 0)",
      "font": "Geist",
      "fs": "16px",
      "fw": "400",
      "ls": "normal",
      "lh": "normal",
      "border": "0px none rgb(255, 255, 255)",
      "radius": "0px",
      "pad": "0px",
      "w": 20,
      "h": 25
    },
    {
      "tag": "svg",
      "cls": "[object SVGAnimatedString]",
      "text": "",
      "color": "rgb(255, 255, 255)",
      "bg": "rgba(0, 0, 0, 0)",
      "font": "Geist",
      "fs": "16px",
      "fw": "400",
      "ls": "normal",
      "lh": "normal",
      "border": "0px none rgb(255, 255, 255)",
      "radius": "0px",
      "pad": "0px",
      "w": 20,
      "h": 20
    },
    {
      "tag": "NAV",
      "cls": "footer-nav",
      "text": "Overview\n\t\t\t\tAbout\n\t\t\t\tCareers\n\t\t\t\tContact\n\t\t\t\tBlog\n\t\t\t\tChan",
      "color": "oklch(0.29 0 0)",
      "bg": "oklch(0.29 0 0)",
      "font": "Geist",
      "fs": "16px",
      "fw": "400",
      "ls": "normal",
      "lh": "normal",
      "border": "",
      "radius": "0px",
      "pad": "16px 32px",
      "w": 1440,
      "h": 51
    },
    {
      "tag": "A",
      "cls": "",
      "text": "Overview",
      "color": "rgb(255, 255, 255)",
      "bg": "rgba(0, 0, 0, 0)",
      "font": "Geist",
      "fs": "14px",
      "fw": "500",
      "ls": "normal",
      "lh": "normal",
      "border": "0px none rgb(255, 255, 255)",
      "radius": "0px",
      "pad": "0px",
      "w": 61,
      "h": 18
    },
    {
      "tag": "A",
      "cls": "",
      "text": "About",
      "color": "rgb(255, 255, 255)",
      "bg": "rgba(0, 0, 0, 0)",
      "font": "Geist",
      "fs": "14px",
      "fw": "500",
      "ls": "normal",
      "lh": "normal",
      "border": "0px none rgb(255, 255, 255)",
      "radius": "0px",
      "pad": "0px",
      "w": 39,
      "h": 18
    },
    {
      "tag": "A",
      "cls": "",
      "text": "Careers",
      "color": "rgb(255, 255, 255)",
      "bg": "rgba(0, 0, 0, 0)",
      "font": "Geist",
      "fs": "14px",
      "fw": "500",
      "ls": "normal",
      "lh": "normal",
      "border": "0px none rgb(255, 255, 255)",
      "radius": "0px",
      "pad": "0px",
      "w": 51,
      "h": 18
    },
    {
      "tag": "A",
      "cls": "",
      "text": "Contact",
      "color": "rgb(255, 255, 255)",
      "bg": "rgba(0, 0, 0, 0)",
      "font": "Geist",
      "fs": "14px",
      "fw": "500",
      "ls": "normal",
      "lh": "normal",
      "border": "0px none rgb(255, 255, 255)",
      "radius": "0px",
      "pad": "0px",
      "w": 52,
      "h": 18
    },
    {
      "tag": "A",
      "cls": "",
      "text": "Blog",
      "color": "rgb(255, 255, 255)",
      "bg": "rgba(0, 0, 0, 0)",
      "font": "Geist",
      "fs": "14px",
      "fw": "500",
      "ls": "normal",
      "lh": "normal",
      "border": "0px none rgb(255, 255, 255)",
      "radius": "0px",
      "pad": "0px",
      "w": 30,
      "h": 18
    },
    {
      "tag": "A",
      "cls": "",
      "text": "Changelog",
      "color": "rgb(255, 255, 255)",
      "bg": "rgba(0, 0, 0, 0)",
      "font": "Geist",
      "fs": "14px",
      "fw": "500",
      "ls": "normal",
      "lh": "normal",
      "border": "0px none rgb(255, 255, 255)",
      "radius": "0px",
      "pad": "0px",
      "w": 71,
      "h": 18
    },
    {
      "tag": "A",
      "cls": "",
      "text": "Pricing",
      "color": "rgb(255, 255, 255)",
      "bg": "rgba(0, 0, 0, 0)",
      "font": "Geist",
      "fs": "14px",
      "fw": "500",
      "ls": "normal",
      "lh": "normal",
      "border": "0px none rgb(255, 255, 255)",
      "radius": "0px",
      "pad": "0px",
      "w": 46,
      "h": 18
    },
    {
      "tag": "DIV",
      "cls": "footer-wordmark",
      "text": "© Copyright Lexington Themes 2026",
      "color": "oklch(0.29 0 0)",
      "bg": "oklch(0.29 0 0)",
      "font": "Geist",
      "fs": "16px",
      "fw": "400",
      "ls": "normal",
      "lh": "normal",
      "border": "0px none oklch(0.29 0 0)",
      "radius": "0px",
      "pad": "32px 0px 0px",
      "w": 1440,
      "h": 492
    },
    {
      "tag": "svg",
      "cls": "[object SVGAnimatedString]",
      "text": "",
      "color": "rgb(255, 255, 255)",
      "bg": "rgba(0, 0, 0, 0)",
      "font": "Geist",
      "fs": "16px",
      "fw": "400",
      "ls": "normal",
      "lh": "normal",
      "border": "0px none rgb(255, 255, 255)",
      "radius": "0px",
      "pad": "0px",
      "w": 1440,
      "h": 396
    },
    {
      "tag": "path",
      "cls": "[object SVGAnimatedString]",
      "text": "",
      "color": "rgb(255, 255, 255)",
      "bg": "rgba(0, 0, 0, 0)",
      "font": "Geist",
      "fs": "16px",
      "fw": "400",
      "ls": "normal",
      "lh": "normal",
      "border": "0px none rgb(255, 255, 255)",
      "radius": "0px",
      "pad": "0px",
      "w": 1438,
      "h": 396
    },
    {
      "tag": "DIV",
      "cls": "footer-copy",
      "text": "© Copyright Lexington Themes 2026",
      "color": "oklab(0.999994 0.0000455677 0.0000200868 / 0.6)",
      "bg": "oklch(0.29 0 0)",
      "font": "Geist",
      "fs": "12px",
      "fw": "400",
      "ls": "normal",
      "lh": "normal",
      "border": "0px none oklab(0.999994 0.0000455677 0.0000200868 / 0.6)",
      "radius": "0px",
      "pad": "16px 32px 32px",
      "w": 1440,
      "h": 64
    }
  ]
}